python_tty/__init__.py
python_tty/console_factory.py
python_tty/audit/__init__.py
python_tty/audit/sink.py
python_tty/audit/ui_logger.py
python_tty/commands/__init__.py
python_tty/commands/core.py
python_tty/commands/decorators.py
python_tty/commands/general.py
python_tty/commands/mixins.py
python_tty/commands/registry.py
python_tty/commands/examples/__init__.py
python_tty/commands/examples/root_commands.py
python_tty/commands/examples/sub_commands.py
python_tty/config/__init__.py
python_tty/config/config.py
python_tty/consoles/__init__.py
python_tty/consoles/core.py
python_tty/consoles/decorators.py
python_tty/consoles/loader.py
python_tty/consoles/manager.py
python_tty/consoles/registry.py
python_tty/consoles/examples/__init__.py
python_tty/consoles/examples/root_console.py
python_tty/consoles/examples/sub_console.py
python_tty/exceptions/__init__.py
python_tty/exceptions/console_exception.py
python_tty/executor/__init__.py
python_tty/executor/executor.py
python_tty/executor/models.py
python_tty/frontends/__init__.py
python_tty/frontends/rpc/__init__.py
python_tty/frontends/web/__init__.py
python_tty/meta/__init__.py
python_tty/runtime/__init__.py
python_tty/runtime/events.py
python_tty/runtime/provider.py
python_tty/runtime/router.py
python_tty/utils/__init__.py
python_tty/utils/table.py
python_tty/utils/tokenize.py
python_tty-0.1.6.dist-info/licenses/LICENSE
python_tty-0.1.6.dist-info/licenses/NOTICE
python_tty-0.1.6.dist-info/METADATA
python_tty-0.1.6.dist-info/WHEEL
python_tty-0.1.6.dist-info/top_level.txt
python_tty-0.1.6.dist-info/RECORD
