Metadata-Version: 2.4
Name: python-tty
Version: 0.1.6
Summary: A multi-console TTY framework for complex CLI/TTY apps
Home-page: https://github.com/ROOKIEMIE/python-tty
Author: ROOKIEMIE
License: Apache-2.0
Classifier: License :: OSI Approved :: Apache Software License
Classifier: Programming Language :: Python :: 3
Classifier: Programming Language :: Python :: 3 :: Only
Requires-Python: >=3.10
License-File: LICENSE
License-File: NOTICE
Requires-Dist: fastapi>=0.110.0
Requires-Dist: grpcio>=1.60.0
Requires-Dist: prompt_toolkit>=3.0.32
Requires-Dist: protobuf>=4.25.0
Requires-Dist: tqdm
Requires-Dist: uvicorn>=0.27.0
Dynamic: author
Dynamic: classifier
Dynamic: description
Dynamic: description-content-type
Dynamic: home-page
Dynamic: license
Dynamic: license-file
Dynamic: requires-dist
Dynamic: requires-python
Dynamic: summary
